genux/__init__.py
genux/agents.py
genux/main.py
genux/orchestrator.py
genux/utils.py
genux-0.1.9.dist-info/licenses/LICENSE
genux-0.1.9.dist-info/METADATA
genux-0.1.9.dist-info/WHEEL
genux-0.1.9.dist-info/entry_points.txt
genux-0.1.9.dist-info/top_level.txt
genux-0.1.9.dist-info/RECORD
