Metadata-Version: 2.4
Name: genux
Version: 0.1.9
Summary: Multi-Agent Linux Command Execution System
Author-email: Ashwin <ashwinkulkarni737@gmail.com>
License: MIT License
Requires-Python: >=3.9
License-File: LICENSE
Requires-Dist: langchain>=0.2.0
Requires-Dist: langchain-groq>=0.1.0
Requires-Dist: langchain-community>=0.2.0
Requires-Dist: tavily-python>=0.3.0
Requires-Dist: langchain-tavily>=0.2.11
Requires-Dist: pyfiglet>=1.0.4
Dynamic: license-file
